CHANGELOG.md
CITATION.cff
COPYING
INSTALL
MANIFEST.in
README.md
compile_externals.py
setup.cfg
setup.py
versioneer.py
data/__init__.py
data/__pycache__/__init__.cpython-310.pyc
data/bg/hg18.MotifSampler.bg
data/bg/hg19.MotifSampler.bg
data/bg/hg38.MotifSampler.bg
data/bg/mm10.MotifSampler.bg
data/bg/mm9.MotifSampler.bg
data/bg/xenTro2.MotifSampler.bg
data/cfg/gimmemotifs.default.cfg
data/examples/Gm12878.CTCF.top500.w200.bed
data/examples/Gm12878.CTCF.top500.w200.fa
data/examples/MA0099.3.jaspar
data/examples/NRF1.bed
data/examples/TAp73alpha.bed
data/examples/TAp73alpha.fa
data/examples/example.pfm
data/examples/hg19.blood.most_variable.10k.txt
data/examples/hg19.blood.most_variable.1k.txt
data/examples/test.small.fa
data/motif_databases/CIS-BP.motif2factors.txt
data/motif_databases/CIS-BP.pfm
data/motif_databases/ENCODE.motif2factors.txt
data/motif_databases/ENCODE.pfm
data/motif_databases/HOCOMOCOv10_HUMAN.motif2factors.txt
data/motif_databases/HOCOMOCOv10_HUMAN.pfm
data/motif_databases/HOCOMOCOv10_MOUSE.motif2factors.txt
data/motif_databases/HOCOMOCOv10_MOUSE.pfm
data/motif_databases/HOCOMOCOv11_HUMAN.motif2factors.txt
data/motif_databases/HOCOMOCOv11_HUMAN.pfm
data/motif_databases/HOCOMOCOv11_MOUSE.motif2factors.txt
data/motif_databases/HOCOMOCOv11_MOUSE.pfm
data/motif_databases/HOMER.motif2factors.txt
data/motif_databases/HOMER.pfm
data/motif_databases/IMAGE.motif2factors.txt
data/motif_databases/IMAGE.pfm
data/motif_databases/JASPAR2018.motif2factors.txt
data/motif_databases/JASPAR2018.pfm
data/motif_databases/JASPAR2018_fungi.motif2factors.txt
data/motif_databases/JASPAR2018_fungi.pfm
data/motif_databases/JASPAR2018_insects.motif2factors.txt
data/motif_databases/JASPAR2018_insects.pfm
data/motif_databases/JASPAR2018_nematodes.motif2factors.txt
data/motif_databases/JASPAR2018_nematodes.pfm
data/motif_databases/JASPAR2018_plants.motif2factors.txt
data/motif_databases/JASPAR2018_plants.pfm
data/motif_databases/JASPAR2018_urochordates.motif2factors.txt
gimmemotifs.egg-info/PKG-INFO
gimmemotifs.egg-info/SOURCES.txt
gimmemotifs.egg-info/dependency_links.txt
gimmemotifs.egg-info/requires.txt
gimmemotifs.egg-info/top_level.txt
