Metadata-Version: 2.1
Name: gimmemotifs
Version: 0.18.0
Summary: GimmeMotifs is a motif prediction pipeline.
Home-page: https://github.com/vanheeringen-lab/gimmemotifs/
Download-URL: https://github.com/vanheeringen-lab/gimmemotifs/tarball/0.18.0
Author: Simon van Heeringen
Author-email: simon.vanheeringen@gmail.com
License: MIT
Classifier: Development Status :: 4 - Beta
Classifier: Intended Audience :: Science/Research
Classifier: License :: OSI Approved :: MIT License
Classifier: Operating System :: MacOS :: MacOS X
Classifier: Operating System :: POSIX :: Linux
Classifier: Programming Language :: Python :: 3
Classifier: Topic :: Scientific/Engineering :: Bio-Informatics
Provides-Extra: ete3
Provides-Extra: notebook
Provides-Extra: xgboost
License-File: COPYING
